test_bob8gook.py
testbob8gook.py
packagesBob8gook-1.0.0.7.dist-info/METADATA
packagesBob8gook-1.0.0.7.dist-info/WHEEL
packagesBob8gook-1.0.0.7.dist-info/top_level.txt
packagesBob8gook-1.0.0.7.dist-info/RECORD
