Metadata-Version: 2.1
Name: packagesBob8gook
Version: 1.0.0.7
Summary: bob8gook
Home-page: https://github.com/woounnan
Author: bob8gook
Author-email: hyeok.jang@lotte.net
License: MIT
Requires-Python: >=3
